gimmetool/__init__.py
gimmetool/gimme.sh
gimmetool/gimmetool.py
gimmetool-0.1.21.dist-info/METADATA
gimmetool-0.1.21.dist-info/WHEEL
gimmetool-0.1.21.dist-info/entry_points.txt
gimmetool-0.1.21.dist-info/RECORD
