Metadata-Version: 2.1
Name: gimmetool
Version: 0.1.21
Summary: The multi-repo manager
Author: Jeff
Author-email: jeffhilton.code@gmail.com
Requires-Python: >=3.8,<4.0
Classifier: Programming Language :: Python :: 3
Classifier: Programming Language :: Python :: 3.8
Classifier: Programming Language :: Python :: 3.9
Classifier: Programming Language :: Python :: 3.10
Classifier: Programming Language :: Python :: 3.11
Classifier: Programming Language :: Python :: 3.12
Requires-Dist: argparse (>=1.4.0,<2.0.0)
Requires-Dist: gitpython (>=3.1.43,<4.0.0)
Requires-Dist: setuptools (>=69.2.0,<70.0.0)
Requires-Dist: termcolor (>=2.4.0,<3.0.0)
